{
  "topics": [
    {
      "topicId": "database-indexing",
      "title": "Database Indexing Explained (Retention 9/10)",
      "priority": 1,
      "publishAt": "2026-05-04T20:30:00Z",
      "tags": ["database", "indexing", "performance", "optimization"]
    },
    {
      "topicId": "system-design-caching",
      "title": "Caching Strategies: The Complete Guide",
      "priority": 2,
      "publishAt": "2026-05-05T09:00:00Z",
      "tags": ["system-design", "caching", "redis", "performance"]
    }
  ],
  "settings": {
    "autoPublish": true,
    "publishInterval": "daily",
    "maxVideosPerDay": 2
  }
}
